[
  {
    "day": "2026-05-20",
    "avg_price": 1.961,
    "min_price": 1.961,
    "max_price": 1.961,
    "readings": 38,
    "snapshots": 2
  },
  {
    "day": "2026-05-21",
    "avg_price": 1.951,
    "min_price": 1.911,
    "max_price": 2.07,
    "readings": 261,
    "snapshots": 8
  },
  {
    "day": "2026-05-22",
    "avg_price": 1.957,
    "min_price": 1.898,
    "max_price": 2.097,
    "readings": 316,
    "snapshots": 10
  },
  {
    "day": "2026-05-23",
    "avg_price": 1.968,
    "min_price": 1.903,
    "max_price": 2.127,
    "readings": 427,
    "snapshots": 13
  },
  {
    "day": "2026-05-24",
    "avg_price": 1.963,
    "min_price": 1.897,
    "max_price": 2.13,
    "readings": 444,
    "snapshots": 14
  },
  {
    "day": "2026-05-25",
    "avg_price": 1.956,
    "min_price": 1.899,
    "max_price": 2.13,
    "readings": 280,
    "snapshots": 9
  },
  {
    "day": "2026-05-26",
    "avg_price": 1.953,
    "min_price": 1.896,
    "max_price": 2.116,
    "readings": 253,
    "snapshots": 8
  },
  {
    "day": "2026-05-27",
    "avg_price": 1.898,
    "min_price": 1.864,
    "max_price": 1.98,
    "readings": 238,
    "snapshots": 7
  }
]